{
    "key": "group_63e569fd59666",
    "title": "Settings: Plugin Settings",
    "fields": [
        {
            "key": "field_63e569fd70f2d",
            "label": "",
            "name": "",
            "type": "message",
            "instructions": "",
            "required": 0,
            "conditional_logic": 0,
            "wrapper": {
                "width": "",
                "class": "",
                "id": ""
            },
            "wpml_cf_preferences": 0,
            "message": "<div style=\"font-size:16px;font-weight:bold;\">NOTE:: These are plugin settings that Quicksilver updates after cloning a database.<\/div>",
            "new_lines": "wpautop",
            "esc_html": 0
        },
        {
            "key": "field_63e56a72d961c",
            "label": "Plugin Settings",
            "name": "plugin_settings",
            "type": "repeater",
            "instructions": "",
            "required": 0,
            "conditional_logic": 0,
            "wrapper": {
                "width": "",
                "class": "",
                "id": ""
            },
            "wpml_cf_preferences": 0,
            "show_in_graphql": 0,
            "collapsed": "",
            "min": 0,
            "max": 0,
            "layout": "row",
            "button_label": "Add Env",
            "sub_fields": [
                {
                    "key": "field_63e56b42a121d",
                    "label": "Environment",
                    "name": "environment",
                    "type": "text",
                    "instructions": "",
                    "required": 0,
                    "conditional_logic": 0,
                    "wrapper": {
                        "width": "",
                        "class": "",
                        "id": ""
                    },
                    "wpml_cf_preferences": 1,
                    "show_in_graphql": 0,
                    "default_value": "",
                    "placeholder": "",
                    "prepend": "",
                    "append": "",
                    "maxlength": ""
                },
                {
                    "key": "field_63e56a94d961d",
                    "label": "Jamstack Preview Endpoint",
                    "name": "jamstack_preview_endpoint",
                    "type": "text",
                    "instructions": "",
                    "required": 0,
                    "conditional_logic": 0,
                    "wrapper": {
                        "width": "",
                        "class": "",
                        "id": ""
                    },
                    "wpml_cf_preferences": 1,
                    "show_in_graphql": 0,
                    "default_value": "",
                    "placeholder": "",
                    "prepend": "",
                    "append": "",
                    "maxlength": ""
                },
                {
                    "key": "field_63e56abcd961e",
                    "label": "Jamstack Deployment Badge url",
                    "name": "jamstack_deployment_badge_url",
                    "type": "text",
                    "instructions": "",
                    "required": 0,
                    "conditional_logic": 0,
                    "wrapper": {
                        "width": "",
                        "class": "",
                        "id": ""
                    },
                    "wpml_cf_preferences": 1,
                    "show_in_graphql": 0,
                    "default_value": "",
                    "placeholder": "",
                    "prepend": "",
                    "append": "",
                    "maxlength": ""
                },
                {
                    "key": "field_63e56ad2d961f",
                    "label": "Jamstack Webhook url",
                    "name": "jamstack_webhook_url",
                    "type": "text",
                    "instructions": "",
                    "required": 0,
                    "conditional_logic": 0,
                    "wrapper": {
                        "width": "",
                        "class": "",
                        "id": ""
                    },
                    "wpml_cf_preferences": 1,
                    "show_in_graphql": 0,
                    "default_value": "",
                    "placeholder": "",
                    "prepend": "",
                    "append": "",
                    "maxlength": ""
                },
                {
                    "key": "field_63e56af9d9620",
                    "label": "Stellate Service Name",
                    "name": "stellate_service_name",
                    "type": "text",
                    "instructions": "",
                    "required": 0,
                    "conditional_logic": 0,
                    "wrapper": {
                        "width": "",
                        "class": "",
                        "id": ""
                    },
                    "wpml_cf_preferences": 1,
                    "show_in_graphql": 0,
                    "default_value": "",
                    "placeholder": "",
                    "prepend": "",
                    "append": "",
                    "maxlength": ""
                },
                {
                    "key": "field_63e56b07d9621",
                    "label": "Stellate Purging Token",
                    "name": "stellate_purging_token",
                    "type": "text",
                    "instructions": "",
                    "required": 0,
                    "conditional_logic": 0,
                    "wrapper": {
                        "width": "",
                        "class": "",
                        "id": ""
                    },
                    "wpml_cf_preferences": 1,
                    "show_in_graphql": 0,
                    "default_value": "",
                    "placeholder": "",
                    "prepend": "",
                    "append": "",
                    "maxlength": ""
                }
            ]
        }
    ],
    "location": [
        [
            {
                "param": "options_page",
                "operator": "==",
                "value": "plugin-settings"
            }
        ]
    ],
    "menu_order": 0,
    "position": "normal",
    "style": "default",
    "label_placement": "top",
    "instruction_placement": "label",
    "hide_on_screen": "",
    "active": true,
    "description": "",
    "show_in_rest": 0,
    "show_in_graphql": 0,
    "graphql_field_name": "settings:MarketoApi",
    "map_graphql_types_from_location_rules": 0,
    "graphql_types": "",
    "modified": 1676035350
}