{
    "key": "group_609ece9c01b1a",
    "title": "Content Blocks: Default Template",
    "fields": [
        {
            "key": "field_609ecebd75cce",
            "label": "Main Content",
            "name": "main_content",
            "type": "wysiwyg",
            "instructions": "",
            "required": 0,
            "conditional_logic": 0,
            "wrapper": {
                "width": "",
                "class": "",
                "id": ""
            },
            "wpml_cf_preferences": 0,
            "show_in_graphql": 1,
            "default_value": "",
            "tabs": "all",
            "toolbar": "full",
            "media_upload": 1,
            "delay": 0
        }
    ],
    "location": [
        [
            {
                "param": "page_template",
                "operator": "==",
                "value": "default"
            }
        ]
    ],
    "menu_order": 50,
    "position": "acf_after_title",
    "style": "default",
    "label_placement": "top",
    "instruction_placement": "label",
    "hide_on_screen": "",
    "active": true,
    "description": "",
    "show_in_rest": 0,
    "show_in_graphql": 0,
    "graphql_field_name": "contentBlocks:DefaultTemplate",
    "map_graphql_types_from_location_rules": 0,
    "graphql_types": "",
    "modified": 1660987832
}